{
  "얼음팩 지성피부": "p1",
  "얼음팩 건조피부": "p2",
  "기미차단템": "p3",
  "스타터팩 B": "p4",
  "스타터팩 A": "p5",
  "쫀광모공 3스텝": "p6",
  "여드름": "p7",
  "블블니기미슈젝": "p8",
  "블블 니기미": "p9",
  "세안": "p10",
  "모공잡티": "p11",
  "장벽": "p12",
  "루티너 슈젝": "p13",
  "수면크림": "p14",
  "물광얼음": "p15",
  "완벽한 파데프리": "p16",
  "어려보여 파데프리": "p17",
  "그린잘팩": "p18",
  "물먹화장": "p19",
  "필쥬란 크림": "p20",
  "파니쉬": "p21",
  "메가실리엄": "p22",
  "파메키 프로모션": "p23",
  "5월 가정의 달 프로모션": "p24",
  "망각하는자 포마드": "p25",
  "파메스테틱 키": "p26",
  "레빗밴드": "p27",
  "파이널밤": "p28",
  "세멘잘라이트 100ml": "p29",
  "그린박신 스트롱 65ml": "p30",
  "로션폴리싱": "p31",
  "세멘잘 50ml": "p32",
  "겔스타터": "p33",
  "세멘스틱 20개입": "p34",
  "겔폴리싱": "p35",
  "피니쉬로션 20g": "p36",
  "튜토리얼키트": "p37",
  "세멘시트 가방": "p38",
  "그린박신 150ml": "p39",
  "세멘팔트": "p40",
  "세멘잘라이트 필름": "p41",
  "슈퍼젝션 크림": "p42",
  "픽시카": "p43",
  "파이토신 V2": "p44",
  "플루이노": "p45",
  "파이토신 필름 100박스": "p46",
  "루티너 15ml": "p47",
  "마호로사": "p48",
  "블루블러드": "p49",
  "니기미봄므": "p50"
}